jax_utils/__init__.py
jax_utils/common_tensor.py
jax_utils/compilation.py
jax_utils/dynamics.py
jax_utils/gradient.py
jax_utils/jax_tensor.py
jax_utils/markov_decision_process.py
jax_utils/optim.py
jax_utils/pytree.py
jax_utils/tranform.py
jax_utils/typing.py
jax_utils/vectorization.py
ai_helpers_jax_utils-0.1.0a1.dist-info/METADATA
ai_helpers_jax_utils-0.1.0a1.dist-info/WHEEL
ai_helpers_jax_utils-0.1.0a1.dist-info/RECORD
