Metadata-Version: 2.1
Name: ai-helpers-jax-utils
Version: 0.1.0a1
Summary: Common jax utils
Home-page: https://github.com/ai-helpers/jax-utils
Keywords: machine-learning,jax,utils
Author: Corentin Vasseur
Author-email: vasseur.corentin@gmail.com
Requires-Python: >=3.10,<3.11
Classifier: Programming Language :: Python :: 3
Classifier: Programming Language :: Python :: 3.10
Classifier: Topic :: Software Development :: Libraries :: Python Modules
Requires-Dist: jax (>=0.4.28,<0.5.0)
Requires-Dist: jax-dataclasses (>=1.6.0,<2.0.0)
Requires-Dist: matplotlib (>=3.9.0,<4.0.0)
Requires-Dist: optax (>=0.2.2,<0.3.0)
Requires-Dist: ordered-set (>=4.1.0,<5.0.0)
Requires-Dist: tqdm (>=4.66.4,<5.0.0)
Project-URL: Documentation, https://ai-helpers.github.io/jax-utils/
Project-URL: Repository, https://github.com/ai-helpers/jax-utils
